{
  "version": "6.3.1",
  "flags": {},
  "shapes": [
    {
      "label": "ego_passable",
      "points": [
        [
          0.0,
          878.125
        ],
        [
          0.0,
          1280.0
        ],
        [
          720.0,
          1279.3969849246232
        ],
        [
          720.0,
          944.375
        ],
        [
          333.0855855855856,
          714.6621621621622
        ],
        [
          325.2027027027027,
          714.6621621621622
        ]
      ],
      "group_id": null,
      "description": "",
      "shape_type": "polygon",
      "flags": {},
      "mask": null
    },
    {
      "label": "left_barrier",
      "points": [
        [
          0.34334763948500324,
          861.4592274678112
        ],
        [
          0.34334763948500324,
          877.3390557939914
        ],
        [
          326.10360360360363,
          713.5360360360361
        ]
      ],
      "group_id": null,
      "description": "",
      "shape_type": "polygon",
      "flags": {},
      "mask": null
    },
    {
      "label": "left_barrier",
      "points": [
        [
          227.9054054054054,
          738.3108108108108
        ],
        [
          227.68018018018014,
          757.2297297297298
        ],
        [
          241.64414414414412,
          756.7792792792793
        ],
        [
          252.68018018018014,
          750.6981981981983
        ],
        [
          252.68018018018014,
          734.0315315315315
        ],
        [
          242.0945945945946,
          733.3558558558559
        ]
      ],
      "group_id": null,
      "description": "",
      "shape_type": "polygon",
      "flags": {},
      "mask": null
    },
    {
      "label": "ditch",
      "points": [
        [
          718.9403973509934,
          856.5562913907285
        ],
        [
          719.6026490066225,
          945.9602649006622
        ],
        [
          332.24264705882354,
          712.2426470588235
        ]
      ],
      "group_id": null,
      "description": "",
      "shape_type": "polygon",
      "flags": {},
      "mask": null
    },
    {
      "label": "tunnel_wall",
      "points": [
        [
          0.8227848101266204,
          742.5316455696202
        ],
        [
          0.1898734177215573,
          858.9873417721518
        ],
        [
          227.5704989154013,
          757.1366594360087
        ],
        [
          226.70281995661605,
          738.0477223427332
        ],
        [
          241.67028199566158,
          732.6247288503254
        ],
        [
          253.8177874186551,
          733.058568329718
        ],
        [
          254.11764705882354,
          744.7058823529412
        ],
        [
          280.98039215686276,
          732.9411764705883
        ],
        [
          281.3422818791946,
          720.9395973154362
        ],
        [
          288.5906040268456,
          719.8657718120805
        ],
        [
          293.8972431077694,
          720.2005012531329
        ],
        [
          293.9597315436242,
          726.3087248322147
        ],
        [
          323.758389261745,
          712.8859060402684
        ],
        [
          324.0268456375839,
          710.738255033557
        ]
      ],
      "group_id": null,
      "description": "",
      "shape_type": "polygon",
      "flags": {},
      "mask": null
    },
    {
      "label": "left_barrier",
      "points": [
        [
          281.3659147869674,
          721.3283208020051
        ],
        [
          281.37254901960785,
          731.1764705882354
        ],
        [
          287.843137254902,
          730.7843137254903
        ],
        [
          293.5294117647059,
          728.0392156862746
        ],
        [
          293.52130325814534,
          720.701754385965
        ],
        [
          288.63408521303256,
          720.4511278195489
        ]
      ],
      "group_id": null,
      "description": "",
      "shape_type": "polygon",
      "flags": {},
      "mask": null
    }
  ],
  "imagePath": "11d80f_0004.jpg",
  "imageData": null,
  "imageHeight": 1280,
  "imageWidth": 720
}